Miniengine/__init__.py
Miniengine-0.0.1.dist-info/LICENSE
Miniengine-0.0.1.dist-info/METADATA
Miniengine-0.0.1.dist-info/WHEEL
Miniengine-0.0.1.dist-info/top_level.txt
Miniengine-0.0.1.dist-info/RECORD
