Metadata-Version: 2.1
Name: Miniengine
Version: 0.0.1
Summary: Engine for pygame
Home-page: 
Author: Rafael Rayes
Author-email: rafa@rayes.com.br
Classifier: Programming Language :: Python :: 3
Classifier: License :: OSI Approved :: MIT License
Classifier: Operating System :: OS Independent
License-File: LICENSE
